django_heythere-1.0.1.dist-info/DESCRIPTION.rst
django_heythere-1.0.1.dist-info/METADATA
django_heythere-1.0.1.dist-info/pydist.json
django_heythere-1.0.1.dist-info/RECORD
django_heythere-1.0.1.dist-info/top_level.txt
django_heythere-1.0.1.dist-info/WHEEL
heythere/__init__.py
heythere/admin.py
heythere/models.py
heythere/settings.py
heythere/utils.py
