Metadata-Version: 2.0
Name: django-heythere
Version: 1.0.1
Summary: Convient notifications for users.
Home-page: https://github.com/brack3t/django-heythere/
Author: Kenneth Love <kenneth@brack3t.com>, Chris Jones <chris@brack3t.com>
Author-email: devs@brack3t.com
License: BSD
Keywords: django,notifications
Platform: UNKNOWN
Classifier: Programming Language :: Python
Classifier: Topic :: Software Development :: Libraries :: Python Modules
Classifier: Framework :: Django
Classifier: Environment :: Web Environment
Classifier: Development Status :: 5 - Production/Stable
Classifier: Programming Language :: Python :: 2.6
Classifier: Programming Language :: Python :: 2.7
Classifier: Programming Language :: Python :: 3.3
